raytracing/__init__.py
raytracing/__main__.py
raytracing/_version.py
raytracing/axicon.py
raytracing/components.py
raytracing/eo.py
raytracing/figure.py
raytracing/gaussianbeam.py
raytracing/graphicComponents.py
raytracing/graphics.py
raytracing/imagingpath.py
raytracing/interface.py
raytracing/lasercavity.py
raytracing/laserpath.py
raytracing/lensViewer.py
raytracing/materials.py
raytracing/matrix.py
raytracing/matrixgroup.py
raytracing/nikon.py
raytracing/olympus.py
raytracing/preferences.py
raytracing/ray.py
raytracing/rays.py
raytracing/specialtylenses.py
raytracing/test.py
raytracing/thorlabs.py
raytracing/utils.py
raytracing/zemax.py
raytracing/examples/__init__.py
raytracing/examples/confocalDetection.py
raytracing/examples/envexamples.py
raytracing/examples/ex01.py
raytracing/examples/ex02.py
raytracing/examples/ex03.py
raytracing/examples/ex04.py
raytracing/examples/ex05.py
raytracing/examples/ex06.py
raytracing/examples/ex07.py
raytracing/examples/ex08.py
raytracing/examples/ex09.py
raytracing/examples/ex10.py
raytracing/examples/ex11.py
raytracing/examples/ex12.py
raytracing/examples/ex13.py
raytracing/examples/ex14.py
raytracing/examples/ex15.py
raytracing/examples/ex16.py
raytracing/examples/ex17.py
raytracing/examples/ex18.py
raytracing/examples/ex19.py
raytracing/examples/fig6-lsmConfocalpinhole.py
raytracing/examples/fig7-kohler.py
raytracing/examples/fig8-widefield.py
raytracing/examples/illuminator.py
raytracing/examples/invariant.py
raytracing/examples/invariantAndEfficiency.py
raytracing/examples/kohlerAndInvariant.py
raytracing/examples/laserScanningMicroscope.py
raytracing/examples/multiProcessingTracing.py
raytracing/examples/randomLambertianRays.py
raytracing/examples/randomUniformRays.py
raytracing/examples/sourceCollection.py
raytracing/examples/template.py
raytracing/examples/twoPhotonDescannedDetector.py
raytracing/specifications/envtest.py
raytracing/specifications/lensBuilder.py
raytracing/tests/envtest.py
raytracing-1.3.16.dist-info/licenses/LICENSE
raytracing-1.3.16.dist-info/METADATA
raytracing-1.3.16.dist-info/WHEEL
raytracing-1.3.16.dist-info/top_level.txt
raytracing-1.3.16.dist-info/RECORD
