Metadata-Version: 2.4
Name: raytracing
Version: 1.3.16
Summary: Simple optical ray tracing library to validate the design of an optical system.
Author-email: Daniel Cote <dccote@cervo.ulaval.ca>
License: MIT
Project-URL: Homepage, https://github.com/DCC-Lab/RayTracing
Keywords: optics,optical,lens,ray tracing,matrix,matrices,aperture,field stop,monte carlo,design,raytracing,zemax,chromatic aberrations
Classifier: Development Status :: 5 - Production/Stable
Classifier: Intended Audience :: Science/Research
Classifier: Intended Audience :: Education
Classifier: Topic :: Scientific/Engineering :: Physics
Classifier: Topic :: Scientific/Engineering :: Visualization
Classifier: Topic :: Education
Classifier: License :: OSI Approved :: MIT License
Classifier: Programming Language :: Python :: 3
Classifier: Programming Language :: Python :: 3.6
Classifier: Programming Language :: Python :: 3.7
Classifier: Programming Language :: Python :: 3.8
Classifier: Programming Language :: Python :: 3.9
Classifier: Programming Language :: Python :: 3.10
Classifier: Programming Language :: Python :: 3.11
Classifier: Programming Language :: Python :: 3.12
Classifier: Programming Language :: Python :: 3.13
Classifier: Operating System :: OS Independent
Requires-Python: >=3.6
License-File: LICENSE
Requires-Dist: matplotlib>=3.7
Requires-Dist: numpy
Requires-Dist: pygments
Requires-Dist: mytk
Dynamic: license-file
